[
{
  "model": "composer.routelsabinding",
  "pk": 1810,
  "fields": {
    "lsa": "4680",
    "route": 113,
    "corresponding_constellation": 2,
    "corresponding_route_error": 2,
    "confirmed": false
  }
},
{
  "model": "composer.routelsabinding",
  "pk": 1811,
  "fields": {
    "lsa": "4681",
    "route": 113,
    "corresponding_constellation": 2,
    "corresponding_route_error": 2,
    "confirmed": false
  }
},
{
  "model": "composer.routelsabinding",
  "pk": 1812,
  "fields": {
    "lsa": "6317",
    "route": 113,
    "corresponding_constellation": 1,
    "corresponding_route_error": null,
    "confirmed": true
  }
},
{
  "model": "composer.routelsabinding",
  "pk": 1813,
  "fields": {
    "lsa": "6377",
    "route": 113,
    "corresponding_constellation": 2,
    "corresponding_route_error": null,
    "confirmed": true
  }
},
{
  "model": "composer.routelsabinding",
  "pk": 1814,
  "fields": {
    "lsa": "7229",
    "route": 113,
    "corresponding_constellation": 2,
    "corresponding_route_error": 2,
    "confirmed": false
  }
},
{
  "model": "composer.routelsabinding",
  "pk": 1815,
  "fields": {
    "lsa": "7658",
    "route": 113,
    "corresponding_constellation": 2,
    "corresponding_route_error": 2,
    "confirmed": false
  }
},
{
  "model": "composer.routelsabinding",
  "pk": 1816,
  "fields": {
    "lsa": "7744",
    "route": 113,
    "corresponding_constellation": 6,
    "corresponding_route_error": 3,
    "confirmed": false
  }
},
{
  "model": "composer.routelsabinding",
  "pk": 1817,
  "fields": {
    "lsa": "7785",
    "route": 113,
    "corresponding_constellation": 2,
    "corresponding_route_error": 3,
    "confirmed": false
  }
},
{
  "model": "composer.routelsabinding",
  "pk": 1818,
  "fields": {
    "lsa": "8139",
    "route": 113,
    "corresponding_constellation": 2,
    "corresponding_route_error": null,
    "confirmed": true
  }
}
]
