[
{
  "model": "composer.routelsabinding",
  "pk": null,
  "fields": {
    "lsa": "153_26",
    "route": 91,
    "corresponding_constellation": null,
    "corresponding_route_error": null,
    "confirmed": true
  }
},
{
  "model": "composer.routelsabinding",
  "pk": null,
  "fields": {
    "lsa": "153_27",
    "route": 91,
    "corresponding_constellation": null,
    "corresponding_route_error": null,
    "confirmed": true
  }
},
{
  "model": "composer.routelsabinding",
  "pk": null,
  "fields": {
    "lsa": "602_1",
    "route": 91,
    "corresponding_constellation": null,
    "corresponding_route_error": null,
    "confirmed": true
  }
},
{
  "model": "composer.routelsabinding",
  "pk": null,
  "fields": {
    "lsa": "813_46",
    "route": 91,
    "corresponding_constellation": null,
    "corresponding_route_error": null,
    "confirmed": true
  }
},
{
  "model": "composer.routelsabinding",
  "pk": null,
  "fields": {
    "lsa": "941_27",
    "route": 91,
    "corresponding_constellation": null,
    "corresponding_route_error": null,
    "confirmed": true
  }
},
{
  "model": "composer.routelsabinding",
  "pk": null,
  "fields": {
    "lsa": "778_1",
    "route": 91,
    "corresponding_constellation": null,
    "corresponding_route_error": null,
    "confirmed": true
  }
},
{
  "model": "composer.routelsabinding",
  "pk": null,
  "fields": {
    "lsa": "321_23",
    "route": 91,
    "corresponding_constellation": null,
    "corresponding_route_error": null,
    "confirmed": true
  }
},
{
  "model": "composer.routelsabinding",
  "pk": null,
  "fields": {
    "lsa": "1563_2",
    "route": 91,
    "corresponding_constellation": null,
    "corresponding_route_error": null,
    "confirmed": true
  }
},
{
  "model": "composer.routelsabinding",
  "pk": null,
  "fields": {
    "lsa": "941_28",
    "route": 91,
    "corresponding_constellation": null,
    "corresponding_route_error": null,
    "confirmed": true
  }
},
{
  "model": "composer.routelsabinding",
  "pk": null,
  "fields": {
    "lsa": "131_39",
    "route": 91,
    "corresponding_constellation": null,
    "corresponding_route_error": null,
    "confirmed": true
  }
},
{
  "model": "composer.routelsabinding",
  "pk": null,
  "fields": {
    "lsa": "131_40",
    "route": 91,
    "corresponding_constellation": null,
    "corresponding_route_error": null,
    "confirmed": true
  }
},
{
  "model": "composer.routelsabinding",
  "pk": null,
  "fields": {
    "lsa": "131_31",
    "route": 91,
    "corresponding_constellation": null,
    "corresponding_route_error": null,
    "confirmed": true
  }
},
{
  "model": "composer.routelsabinding",
  "pk": null,
  "fields": {
    "lsa": "131_32",
    "route": 91,
    "corresponding_constellation": null,
    "corresponding_route_error": null,
    "confirmed": true
  }
},
{
  "model": "composer.routelsabinding",
  "pk": null,
  "fields": {
    "lsa": "133_23",
    "route": 91,
    "corresponding_constellation": null,
    "corresponding_route_error": null,
    "confirmed": true
  }
},
{
  "model": "composer.routelsabinding",
  "pk": null,
  "fields": {
    "lsa": "133_28",
    "route": 91,
    "corresponding_constellation": null,
    "corresponding_route_error": null,
    "confirmed": true
  }
},
{
  "model": "composer.routelsabinding",
  "pk": null,
  "fields": {
    "lsa": "161_40",
    "route": 91,
    "corresponding_constellation": null,
    "corresponding_route_error": null,
    "confirmed": true
  }
},
{
  "model": "composer.routelsabinding",
  "pk": null,
  "fields": {
    "lsa": "307_34",
    "route": 91,
    "corresponding_constellation": null,
    "corresponding_route_error": null,
    "confirmed": true
  }
}
]
