{
  "route": [
    {
      "lon": 9.990909,
      "lat": 53.560863,
      "alt": 9.99
    },
    {
      "lon": 9.990767,
      "lat": 53.560999,
      "alt": 10.75
    },
    {
      "lon": 9.99014,
      "lat": 53.561508,
      "alt": 11.23
    },
    {
      "lon": 9.990121,
      "lat": 53.561491,
      "alt": 11.23
    },
    {
      "lon": 9.989703,
      "lat": 53.561676,
      "alt": 11.4
    },
    {
      "lon": 9.988693,
      "lat": 53.56219,
      "alt": 14.87
    },
    {
      "lon": 9.986637,
      "lat": 53.563238,
      "alt": 16.7
    },
    {
      "lon": 9.986339,
      "lat": 53.563402,
      "alt": 18.05
    },
    {
      "lon": 9.986296,
      "lat": 53.563496,
      "alt": 18.04
    },
    {
      "lon": 9.986215,
      "lat": 53.563552,
      "alt": 18.09
    },
    {
      "lon": 9.985627,
      "lat": 53.563825,
      "alt": 20.2
    },
    {
      "lon": 9.985336,
      "lat": 53.563915,
      "alt": 20.08
    },
    {
      "lon": 9.984938,
      "lat": 53.564063,
      "alt": 18.97
    },
    {
      "lon": 9.984857,
      "lat": 53.564074,
      "alt": 18.97
    },
    {
      "lon": 9.98478189110756,
      "lat": 53.56406370635777,
      "alt": 18.97
    },
    {
      "lon": 9.984695,
      "lat": 53.564082,
      "alt": 18.97
    },
    {
      "lon": 9.984599,
      "lat": 53.564078,
      "alt": 18.52
    },
    {
      "lon": 9.984134,
      "lat": 53.564141,
      "alt": 17.7
    },
    {
      "lon": 9.984049,
      "lat": 53.564059,
      "alt": 18.12
    },
    {
      "lon": 9.983608,
      "lat": 53.564107,
      "alt": 17.68
    },
    {
      "lon": 9.983173,
      "lat": 53.564135,
      "alt": 17.16
    },
    {
      "lon": 9.98275,
      "lat": 53.564148,
      "alt": 16.88
    },
    {
      "lon": 9.98213991522789,
      "lat": 53.564148136717584,
      "alt": 18.97
    },
    {
      "lon": 9.980824,
      "lat": 53.564151,
      "alt": 18.54
    },
    {
      "lon": 9.97914,
      "lat": 53.564222,
      "alt": 19.72
    },
    {
      "lon": 9.978886,
      "lat": 53.564321,
      "alt": 20.08
    },
    {
      "lon": 9.978001,
      "lat": 53.564378,
      "alt": 20.22
    }
  ]
}