[
{
  "model": "composer.routelsabinding",
  "pk": 1735,
  "fields": {
    "lsa": "5814",
    "route": 101,
    "corresponding_constellation": 2,
    "corresponding_route_error": 2,
    "confirmed": false
  }
},
{
  "model": "composer.routelsabinding",
  "pk": 1736,
  "fields": {
    "lsa": "5978",
    "route": 101,
    "corresponding_constellation": 2,
    "corresponding_route_error": 2,
    "confirmed": false
  }
},
{
  "model": "composer.routelsabinding",
  "pk": 1737,
  "fields": {
    "lsa": "5981",
    "route": 101,
    "corresponding_constellation": 2,
    "corresponding_route_error": 2,
    "confirmed": false
  }
},
{
  "model": "composer.routelsabinding",
  "pk": 1738,
  "fields": {
    "lsa": "6102",
    "route": 101,
    "corresponding_constellation": 1,
    "corresponding_route_error": null,
    "confirmed": true
  }
},
{
  "model": "composer.routelsabinding",
  "pk": 1739,
  "fields": {
    "lsa": "9016",
    "route": 101,
    "corresponding_constellation": 7,
    "corresponding_route_error": null,
    "confirmed": true
  }
},
{
  "model": "composer.routelsabinding",
  "pk": 1740,
  "fields": {
    "lsa": "9882",
    "route": 101,
    "corresponding_constellation": 2,
    "corresponding_route_error": 2,
    "confirmed": false
  }
}
]
